tec/__init__.py
tec/ic/__init__.py
tec/ic/ia/__init__.py
tec/ic/ia/pc1/__init__.py
tec/ic/ia/pc1/g07.py
tec.ic.ia.pc1.g07-1.0.1.dist-info/DESCRIPTION.rst
tec.ic.ia.pc1.g07-1.0.1.dist-info/METADATA
tec.ic.ia.pc1.g07-1.0.1.dist-info/RECORD
tec.ic.ia.pc1.g07-1.0.1.dist-info/WHEEL
tec.ic.ia.pc1.g07-1.0.1.dist-info/metadata.json
tec.ic.ia.pc1.g07-1.0.1.dist-info/top_level.txt
