Metadata-Version: 2.0
Name: tec.ic.ia.pc1.g07
Version: 1.0.1
Summary: Generador de muestras basados en los resultados electorales presidenciales de la primera ronda en Costa Rica.
Home-page: https://github.com/mamemo/PC1
Author: Trifuerza
Author-email: UNKNOWN
License: UNKNOWN
Platform: UNKNOWN
